numcodecs_wasm_stochastic_rounding/__init__.py
numcodecs_wasm_stochastic_rounding/__init__.pyi
numcodecs_wasm_stochastic_rounding/codec.wasm
numcodecs_wasm_stochastic_rounding/py.typed
numcodecs_wasm_stochastic_rounding-0.2.0.dist-info/METADATA
numcodecs_wasm_stochastic_rounding-0.2.0.dist-info/WHEEL
numcodecs_wasm_stochastic_rounding-0.2.0.dist-info/entry_points.txt
numcodecs_wasm_stochastic_rounding-0.2.0.dist-info/top_level.txt
numcodecs_wasm_stochastic_rounding-0.2.0.dist-info/RECORD
